{
    "config" : {
        "name" : "",
        "color" : [0, 0, 0]
    },

    "embed" : {
        "header" : {
            "title" : "",
            "description" : "",
            "url" : ""
        },

        "author" : {
            "icon" : "",
            "name" : "",
            "url" : ""
        },

        "content" : {
            "image" : "",
            "field" : [
                {
                    "name" : "",
                    "value" : "",
                    "inline" : false
                }
            ]
        },

        "footer" : {
            "text" : ""
        }
    }
}